MANIFEST.in
README.rst
setup.py
plone/__init__.py
plone.app.toolbar.egg-info/PKG-INFO
plone.app.toolbar.egg-info/SOURCES.txt
plone.app.toolbar.egg-info/dependency_links.txt
plone.app.toolbar.egg-info/entry_points.txt
plone.app.toolbar.egg-info/namespace_packages.txt
plone.app.toolbar.egg-info/not-zip-safe
plone.app.toolbar.egg-info/requires.txt
plone.app.toolbar.egg-info/test_info.txt
plone.app.toolbar.egg-info/top_level.txt
plone/app/__init__.py
plone/app/toolbar/__init__.py
plone/app/toolbar/bbb.py
plone/app/toolbar/bbb.zcml
plone/app/toolbar/bbb_nullviewlet.pt
plone/app/toolbar/bbb_personal_bar.pt
plone/app/toolbar/configure.zcml
plone/app/toolbar/interfaces.py
plone/app/toolbar/testing.py
plone/app/toolbar/toolbar.pt
plone/app/toolbar/toolbar.py
plone/app/toolbar/browser/__init__.py
plone/app/toolbar/browser/configure.zcml
plone/app/toolbar/browser/folder.py
plone/app/toolbar/browser/portlets.py
plone/app/toolbar/browser/templates/folder_contents.pt
plone/app/toolbar/browser/templates/manage_portlets.pt
plone/app/toolbar/profiles/bbb/metadata.xml
plone/app/toolbar/profiles/bbb/viewlets.xml
plone/app/toolbar/profiles/default/actions.xml
plone/app/toolbar/profiles/default/browserlayer.xml
plone/app/toolbar/profiles/default/cssregistry.xml
plone/app/toolbar/profiles/default/jsregistry.xml
plone/app/toolbar/profiles/default/metadata.xml
plone/app/toolbar/profiles/default/registry.xml
plone/app/toolbar/profiles/default/rolemap.xml
plone/app/toolbar/profiles/default/skins.xml
plone/app/toolbar/profiles/uninstall/actions.xml
plone/app/toolbar/profiles/uninstall/cssregistry.xml
plone/app/toolbar/profiles/uninstall/jsregistry.xml
plone/app/toolbar/static/toolbar-fontawesome-webfont.eot
plone/app/toolbar/static/toolbar-fontawesome-webfont.svg
plone/app/toolbar/static/toolbar-fontawesome-webfont.ttf
plone/app/toolbar/static/toolbar-fontawesome-webfont.woff
plone/app/toolbar/static/toolbar-glyphicons-halflings-white.png
plone/app/toolbar/static/toolbar-glyphicons-halflings.png
plone/app/toolbar/static/toolbar-icomoon-small.eot
plone/app/toolbar/static/toolbar-icomoon-small.svg
plone/app/toolbar/static/toolbar-icomoon-small.ttf
plone/app/toolbar/static/toolbar-icomoon-small.woff
plone/app/toolbar/static/toolbar-icomoon.eot
plone/app/toolbar/static/toolbar-icomoon.svg
plone/app/toolbar/static/toolbar-icomoon.ttf
