Metadata-Version: 1.1
Name: plone.app.toolbar
Version: 1.4.0
Summary: Toolbar for Plone
Home-page: https://github.com/plone/plone.app.toolbar
Author: Rok Garbas
Author-email: rok@garbas.si
License: GPL
Keywords: plone ui toolbar
Platform: UNKNOWN
Classifier: Framework :: Plone
Classifier: Programming Language :: Python
Classifier: Topic :: Software Development :: Libraries :: Python Modules
